Metadata-Version: 1.0
Name: distributions-zub1984
Version: 0.1
Summary: Gaussian distributions
Home-page: UNKNOWN
Author: Jubair
Author-email: something@gmail.com
License: UNKNOWN
Platform: UNKNOWN
